sepia2_client_py/__init__.py
sepia2_client_py/api_pb2.py
sepia2_client_py/api_pb2.pyi
sepia2_client_py/api_pb2_grpc.py
sepia2_client_py/py.typed
sepia2_client_py-0.3.0.dist-info/METADATA
sepia2_client_py-0.3.0.dist-info/WHEEL
sepia2_client_py-0.3.0.dist-info/top_level.txt
sepia2_client_py-0.3.0.dist-info/RECORD
