Metadata-Version: 2.4
Name: sepia2-client-py
Version: 0.3.0
Summary: Sepia2 gRPC client for python, automatically derived from current proto definition
Requires-Python: >=3.7
Requires-Dist: grpcio-tools>=1.71.0
Requires-Dist: setuptools
